maxerial_license_verifier/__init__.py
maxerial_license_verifier/client.py
maxerial_license_verifier-0.3.0.dist-info/METADATA
maxerial_license_verifier-0.3.0.dist-info/WHEEL
maxerial_license_verifier-0.3.0.dist-info/top_level.txt
maxerial_license_verifier-0.3.0.dist-info/RECORD
